stexus/__init__.py
stexus/__main__.py
stexus/__version__.py
stexus/cmd.py
stexus/adjust/AdjustException.py
stexus/adjust/AdjustInterface.py
stexus/adjust/AdjustOptuna.py
stexus/adjust/BaseAdjust.py
stexus/adjust/__init__.py
stexus/config/Config.py
stexus/config/ConfigException.py
stexus/config/__init__.py
stexus/experiment/BaseExperiment.py
stexus/experiment/ExperimentException.py
stexus/experiment/ExperimentInterface.py
stexus/experiment/ExperimentWithScript.py
stexus/experiment/__init__.py
stexus/observe/BaseObserve.py
stexus/observe/ObserveException.py
stexus/observe/ObserveInterface.py
stexus/observe/ObserveOptuna.py
stexus/observe/__init__.py
stexus/study/BaseStudy.py
stexus/study/StudyException.py
stexus/study/StudyInterface.py
stexus/study/StudyOptuna.py
stexus/study/__init__.py
stexus-0.0.1.dist-info/licenses/LICENSE
stexus-0.0.1.dist-info/METADATA
stexus-0.0.1.dist-info/WHEEL
stexus-0.0.1.dist-info/top_level.txt
stexus-0.0.1.dist-info/RECORD
