Metadata-Version: 2.4
Name: stexus
Version: 0.0.1
License-Expression: Apache-2.0
License-File: LICENSE
Requires-Dist: alembic==1.16.5
Requires-Dist: bottle==0.13.4
Requires-Dist: Cerberus==1.3.7
Requires-Dist: colorlog==6.9.0
Requires-Dist: greenlet==3.2.4
Requires-Dist: Jinja2==3.1.6
Requires-Dist: joblib==1.5.2
Requires-Dist: Mako==1.3.10
Requires-Dist: MarkupSafe==3.0.2
Requires-Dist: numpy==2.3.2
Requires-Dist: optuna==4.5.0
Requires-Dist: optuna-dashboard==0.19.0
Requires-Dist: packaging==25.0
Requires-Dist: PyYAML==6.0.2
Requires-Dist: scikit-learn==1.7.1
Requires-Dist: scipy==1.16.1
Requires-Dist: SQLAlchemy==2.0.43
Requires-Dist: threadpoolctl==3.6.0
Requires-Dist: tqdm==4.67.1
Requires-Dist: typing_extensions==4.15.0
Provides-Extra: dev
Dynamic: license-file
